{"_default": {}, "boltnames": {"1": {"type": "Hexagon socket set screw with cone point", "name": "4027"}, "2": {"type": "Hexagon socket set screw with cone point", "name": "4029"}, "3": {"type": "Countersunk raised head screws", "name": "14584"}, "4": {"type": "Countersunk raised head screws", "name": "7047"}, "5": {"type": "Countersunk flat head screws", "name": "7046-2"}, "6": {"type": "Button Head Screw", "name": "7380"}, "7": {"type": "Countersunk flat head screws", "name": "10642"}, "8": {"type": "Countersunk raised head screws", "name": "14581"}, "9": {"type": "Cup head screw low head", "name": "7984"}, "10": {"type": "Cup head screws", "name": "4762"}, "11": {"type": "Hexagon Head Bolts", "name": "4014"}, "12": {"type": "Cup head square neck bolts", "name": "603"}, "13": {"type": "Hexagon Head Screws", "name": "4017"}}, "washernames": {"1": {"std": 7089, "type": "Plain Washer"}, "2": {"std": 7092, "type": "Plain Washer"}, "3": {"std": "7093-1", "type": "Plain Washer"}, "4": {"std": "7093-2", "type": "Plain Washer"}, "5": {"std": 7349, "type": "Plain Washer"}, "6": {"std": 6796, "type": "CS Washer"}, "7": {"std": "25-510", "type": "CS Washer"}, "8": {"std": "25-511", "type": "Nord Lock Washer"}}, "boltnutmaterial": {"1": {"material": "Steel", "size": 4.6, "Re": 240.0, "Rm": 400.0, "E": 210000.0}, "2": {"material": "Steel", "size": 8.8, "Re": 640.0, "Rm": 800.0, "E": 210000.0}, "3": {"material": "Steel", "size": 10.9, "Re": 900.0, "Rm": 1000.0, "E": 210000.0}, "4": {"material": "Steel", "size": 12.9, "Re": 1080.0, "Rm": 1200.0, "E": 210000.0}, "5": {"material": "Stainless Steel", "size": "A2-70", "Re": 450.0, "Rm": 700.0, "E": 191000.0}, "6": {"material": "Stainless Steel", "size": "A4-80", "Re": 600.0, "Rm": 800.0, "E": 191000.0}}, "nutnames": {"1": {"std": 4032, "type": "Hexagon Nut"}, "2": {"std": 4035, "type": "Hexagon Thin Nut"}, "3": {"std": 7040, "type": "Prevailing Torque type Hex nut. Non Metallic insert."}, "4": {"std": 7042, "type": "Prevailing Torque type. All metal Hex nut."}, "5": {"std": 1587, "type": "Cap Nut high type"}}, "7089": {"1": {"size": 1.6, "dimin": 1.7, "dimax": 1.84, "domin": 3.7, "domax": 4.0, "thnom": 0.3, "thmin": 0.35, "thmax": 0.25, "type": "Nom"}, "2": {"size": 2.0, "dimin": 2.2, "dimax": 2.34, "domin": 4.7, "domax": 5.0, "thnom": 0.3, "thmin": 0.35, "thmax": 0.25, "type": "Nom"}, "3": {"size": 2.5, "dimin": 2.7, "dimax": 2.84, "domin": 5.7, "domax": 6.0, "thnom": 0.5, "thmin": 0.55, "thmax": 0.45, "type": "Nom"}, "4": {"size": 3.0, "dimin": 3.2, "dimax": 3.38, "domin": 6.64, "domax": 7.0, "thnom": 0.5, "thmin": 0.55, "thmax": 0.45, "type": "Nom"}, "5": {"size": 4.0, "dimin": 4.3, "dimax": 4.48, "domin": 8.64, "domax": 9.0, "thnom": 0.8, "thmin": 0.9, "thmax": 0.7, "type": "Nom"}, "6": {"size": 5.0, "dimin": 5.3, "dimax": 5.48, "domin": 9.64, "domax": 10.0, "thnom": 1.0, "thmin": 1.1, "thmax": 0.9, "type": "Nom"}, "7": {"size": 6.0, "dimin": 6.4, "dimax": 6.62, "domin": 11.57, "domax": 12.0, "thnom": 1.6, "thmin": 1.8, "thmax": 1.4, "type": "Nom"}, "8": {"size": 8.0, "dimin": 8.4, "dimax": 8.62, "domin": 15.57, "domax": 16.0, "thnom": 1.6, "thmin": 1.8, "thmax": 1.4, "type": "Nom"}, "9": {"size": 10.0, "dimin": 10.5, "dimax": 10.77, "domin": 19.48, "domax": 20.0, "thnom": 2.0, "thmin": 2.2, "thmax": 1.8, "type": "Nom"}, "10": {"size": 12.0, "dimin": 13.0, "dimax": 13.27, "domin": 23.48, "domax": 24.0, "thnom": 2.5, "thmin": 2.7, "thmax": 2.3, "type": "Nom"}, "11": {"size": 16.0, "dimin": 17.0, "dimax": 17.27, "domin": 29.48, "domax": 30.0, "thnom": 3.0, "thmin": 3.3, "thmax": 2.7, "type": "Nom"}, "12": {"size": 20.0, "dimin": 21.0, "dimax": 21.33, "domin": 36.38, "domax": 37.0, "thnom": 3.0, "thmin": 3.3, "thmax": 2.7, "type": "Nom"}, "13": {"size": 24.0, "dimin": 25.0, "dimax": 25.33, "domin": 43.38, "domax": 44.0, "thnom": 4.0, "thmin": 4.3, "thmax": 3.7, "type": "Nom"}, "14": {"size": 30.0, "dimin": 31.0, "dimax": 31.39, "domin": 55.26, "domax": 56.0, "thnom": 4.0, "thmin": 4.3, "thmax": 3.7, "type": "Nom"}, "15": {"size": 36.0, "dimin": 37.0, "dimax": 37.62, "domin": 64.8, "domax": 66.0, "thnom": 5.0, "thmin": 5.6, "thmax": 4.4, "type": "Nom"}, "16": {"size": 42.0, "dimin": 45.0, "dimax": 45.62, "domin": 76.8, "domax": 78.0, "thnom": 8.0, "thmin": 9.0, "thmax": 7.0, "type": "Nom"}, "17": {"size": 48.0, "dimin": 52.0, "dimax": 52.74, "domin": 90.6, "domax": 92.0, "thnom": 8.0, "thmin": 9.0, "thmax": 7.0, "type": "Nom"}, "18": {"size": 56.0, "dimin": 62.0, "dimax": 62.74, "domin": 103.6, "domax": 105.0, "thnom": 10.0, "thmin": 11.0, "thmax": 9.0, "type": "Nom"}, "19": {"size": 64.0, "dimin": 70.0, "dimax": 70.74, "domin": 113.6, "domax": 115.0, "thnom": 10.0, "thmin": 11.0, "thmax": 9.0, "type": "Nom"}}, "7092": {"1": {"size": 1.6, "dimin": 1.7, "dimax": 1.84, "domin": 3.2, "domax": 3.5, "thnom": 0.3, "thmin": 0.35, "thmax": 0.25, "type": "Nom"}, "2": {"size": 2.0, "dimin": 2.2, "dimax": 2.34, "domin": 4.2, "domax": 4.5, "thnom": 0.3, "thmin": 0.35, "thmax": 0.25, "type": "Nom"}, "3": {"size": 2.5, "dimin": 2.7, "dimax": 2.84, "domin": 4.7, "domax": 5.0, "thnom": 0.5, "thmin": 0.55, "thmax": 0.45, "type": "Nom"}, "4": {"size": 3.0, "dimin": 3.2, "dimax": 3.38, "domin": 5.7, "domax": 6.0, "thnom": 0.5, "thmin": 0.55, "thmax": 0.45, "type": "Nom"}, "5": {"size": 4.0, "dimin": 4.3, "dimax": 4.48, "domin": 7.64, "domax": 8.0, "thnom": 0.5, "thmin": 0.55, "thmax": 0.45, "type": "Nom"}, "6": {"size": 5.0, "dimin": 5.3, "dimax": 5.48, "domin": 8.64, "domax": 9.0, "thnom": 1.0, "thmin": 1.1, "thmax": 0.9, "type": "Nom"}, "7": {"size": 6.0, "dimin": 6.4, "dimax": 6.62, "domin": 10.57, "domax": 11.0, "thnom": 1.6, "thmin": 1.8, "thmax": 1.4, "type": "Nom"}, "8": {"size": 8.0, "dimin": 8.4, "dimax": 8.62, "domin": 14.57, "domax": 15.0, "thnom": 1.6, "thmin": 1.8, "thmax": 1.4, "type": "Nom"}, "9": {"size": 10.0, "dimin": 10.5, "dimax": 10.77, "domin": 17.57, "domax": 18.0, "thnom": 1.6, "thmin": 1.8, "thmax": 1.4, "type": "Nom"}, "10": {"size": 12.0, "dimin": 13.0, "dimax": 13.27, "domin": 19.48, "domax": 20.0, "thnom": 2.0, "thmin": 2.2, "thmax": 1.8, "type": "Nom"}, "11": {"size": 16.0, "dimin": 17.0, "dimax": 17.27, "domin": 27.48, "domax": 28.0, "thnom": 2.5, "thmin": 2.7, "thmax": 2.3, "type": "Nom"}, "12": {"size": 20.0, "dimin": 21.0, "dimax": 21.33, "domin": 33.38, "domax": 34.0, "thnom": 3.0, "thmin": 3.3, "thmax": 2.7, "type": "Nom"}, "13": {"size": 24.0, "dimin": 25.0, "dimax": 25.33, "domin": 38.38, "domax": 39.0, "thnom": 4.0, "thmin": 4.3, "thmax": 3.7, "type": "Nom"}, "14": {"size": 30.0, "dimin": 31.0, "dimax": 31.39, "domin": 49.38, "domax": 50.0, "thnom": 4.0, "thmin": 4.3, "thmax": 3.7, "type": "Nom"}, "15": {"size": 36.0, "dimin": 37.0, "dimax": 37.62, "domin": 58.8, "domax": 60.0, "thnom": 5.0, "thmin": 5.6, "thmax": 4.4, "type": "Nom"}}, "7093-1": {"1": {"size": 3.0, "dimin": 3.2, "dimax": 3.38, "domin": 8.64, "domax": 9.0, "thnom": 0.8, "thmin": 0.9, "thmax": 0.7, "type": "Nom"}, "2": {"size": 4.0, "dimin": 4.3, "dimax": 4.48, "domin": 11.57, "domax": 12.0, "thnom": 1.0, "thmin": 1.1, "thmax": 0.9, "type": "Nom"}, "3": {"size": 5.0, "dimin": 5.3, "dimax": 5.48, "domin": 14.57, "domax": 15.0, "thnom": 1.0, "thmin": 1.1, "thmax": 0.9, "type": "Nom"}, "4": {"size": 6.0, "dimin": 6.4, "dimax": 6.62, "domin": 17.57, "domax": 18.0, "thnom": 1.6, "thmin": 1.8, "thmax": 1.4, "type": "Nom"}, "5": {"size": 8.0, "dimin": 8.4, "dimax": 8.62, "domin": 23.48, "domax": 24.0, "thnom": 2.0, "thmin": 2.2, "thmax": 1.8, "type": "Nom"}, "6": {"size": 10.0, "dimin": 10.5, "dimax": 10.77, "domin": 29.48, "domax": 30.0, "thnom": 2.5, "thmin": 2.7, "thmax": 2.3, "type": "Nom"}, "7": {"size": 12.0, "dimin": 13.0, "dimax": 13.27, "domin": 36.38, "domax": 37.0, "thnom": 3.0, "thmin": 3.3, "thmax": 2.7, "type": "Nom"}, "8": {"size": 16.0, "dimin": 17.0, "dimax": 17.27, "domin": 49.38, "domax": 50.0, "thnom": 3.0, "thmin": 3.3, "thmax": 2.7, "type": "Nom"}, "9": {"size": 20.0, "dimin": 21.0, "dimax": 21.33, "domin": 59.26, "domax": 60.0, "thnom": 4.0, "thmin": 4.3, "thmax": 3.7, "type": "Nom"}, "10": {"size": 24.0, "dimin": 25.0, "dimax": 25.52, "domin": 70.8, "domax": 72.0, "thnom": 5.0, "thmin": 5.6, "thmax": 4.4, "type": "Nom"}, "11": {"size": 30.0, "dimin": 33.0, "dimax": 33.62, "domin": 90.6, "domax": 92.0, "thnom": 6.0, "thmin": 6.6, "thmax": 5.4, "type": "Nom"}, "12": {"size": 36.0, "dimin": 39.0, "dimax": 39.62, "domin": 108.6, "domax": 110.0, "thnom": 8.0, "thmin": 9.0, "thmax": 7.0, "type": "Nom"}}, "7093-2": {"1": {"size": 3.0, "dimin": 3.4, "dimax": 3.7, "domin": 8.1, "domax": 9.0, "thnom": 0.8, "thmin": 1.0, "thmax": 0.6, "type": "Nom"}, "2": {"size": 4.0, "dimin": 4.5, "dimax": 4.8, "domin": 10.9, "domax": 12.0, "thnom": 1.0, "thmin": 1.2, "thmax": 0.8, "type": "Nom"}, "3": {"size": 5.0, "dimin": 5.5, "dimax": 5.8, "domin": 13.9, "domax": 15.0, "thnom": 1.0, "thmin": 1.2, "thmax": 0.8, "type": "Nom"}, "4": {"size": 6.0, "dimin": 6.6, "dimax": 6.96, "domin": 16.9, "domax": 18.0, "thnom": 1.6, "thmin": 1.9, "thmax": 1.3, "type": "Nom"}, "5": {"size": 8.0, "dimin": 9.0, "dimax": 9.36, "domin": 22.7, "domax": 24.0, "thnom": 2.0, "thmin": 2.3, "thmax": 1.7, "type": "Nom"}, "6": {"size": 10.0, "dimin": 11.0, "dimax": 11.43, "domin": 28.7, "domax": 30.0, "thnom": 2.5, "thmin": 2.8, "thmax": 2.2, "type": "Nom"}, "7": {"size": 12.0, "dimin": 13.5, "dimax": 13.93, "domin": 35.4, "domax": 37.0, "thnom": 3.0, "thmin": 3.6, "thmax": 2.4, "type": "Nom"}, "8": {"size": 16.0, "dimin": 17.5, "dimax": 17.93, "domin": 48.4, "domax": 50.0, "thnom": 3.0, "thmin": 3.6, "thmax": 2.4, "type": "Nom"}, "9": {"size": 20.0, "dimin": 22.0, "dimax": 22.52, "domin": 58.1, "domax": 60.0, "thnom": 4.0, "thmin": 4.6, "thmax": 3.4, "type": "Nom"}, "10": {"size": 24.0, "dimin": 26.0, "dimax": 26.84, "domin": 70.1, "domax": 72.0, "thnom": 5.0, "thmin": 6.0, "thmax": 4.0, "type": "Nom"}, "11": {"size": 30.0, "dimin": 33.0, "dimax": 34.0, "domin": 89.8, "domax": 92.0, "thnom": 6.0, "thmin": 7.0, "thmax": 5.0, "type": "Nom"}, "12": {"size": 36.0, "dimin": 39.0, "dimax": 40.0, "domin": 107.8, "domax": 110.0, "thnom": 8.0, "thmin": 9.2, "thmax": 6.8, "type": "Nom"}}, "7349": {"1": {"size": 3.0, "dimin": 3.2, "dimax": 0.0, "domin": 9.0, "domax": 0.0, "thnom": 1.0, "thmin": 0.0, "thmax": 0.0, "type": "Nom"}, "2": {"size": 4.0, "dimin": 4.3, "dimax": 0.0, "domin": 12.0, "domax": 0.0, "thnom": 1.6, "thmin": 0.0, "thmax": 0.0, "type": "Nom"}, "3": {"size": 5.0, "dimin": 5.3, "dimax": 0.0, "domin": 15.0, "domax": 0.0, "thnom": 2.0, "thmin": 0.0, "thmax": 0.0, "type": "Nom"}, "4": {"size": 6.0, "dimin": 6.4, "dimax": 0.0, "domin": 17.0, "domax": 0.0, "thnom": 3.0, "thmin": 0.0, "thmax": 0.0, "type": "Nom"}, "5": {"size": 8.0, "dimin": 8.4, "dimax": 0.0, "domin": 21.0, "domax": 0.0, "thnom": 4.0, "thmin": 0.0, "thmax": 0.0, "type": "Nom"}, "6": {"size": 10.0, "dimin": 10.5, "dimax": 0.0, "domin": 25.0, "domax": 0.0, "thnom": 4.0, "thmin": 0.0, "thmax": 0.0, "type": "Nom"}, "7": {"size": 12.0, "dimin": 13.0, "dimax": 0.0, "domin": 30.0, "domax": 0.0, "thnom": 6.0, "thmin": 0.0, "thmax": 0.0, "type": "Nom"}, "8": {"size": 14.0, "dimin": 15.0, "dimax": 0.0, "domin": 36.0, "domax": 0.0, "thnom": 6.0, "thmin": 0.0, "thmax": 0.0, "type": "Nom"}, "9": {"size": 16.0, "dimin": 17.0, "dimax": 0.0, "domin": 40.0, "domax": 0.0, "thnom": 6.0, "thmin": 0.0, "thmax": 0.0, "type": "Nom"}, "10": {"size": 18.0, "dimin": 19.0, "dimax": 0.0, "domin": 44.0, "domax": 0.0, "thnom": 8.0, "thmin": 0.0, "thmax": 0.0, "type": "Nom"}, "11": {"size": 20.0, "dimin": 21.0, "dimax": 0.0, "domin": 44.0, "domax": 0.0, "thnom": 8.0, "thmin": 0.0, "thmax": 0.0, "type": "Nom"}, "12": {"size": 22.0, "dimin": 23.0, "dimax": 0.0, "domin": 50.0, "domax": 0.0, "thnom": 8.0, "thmin": 0.0, "thmax": 0.0, "type": "Nom"}, "13": {"size": 24.0, "dimin": 25.0, "dimax": 0.0, "domin": 50.0, "domax": 0.0, "thnom": 10.0, "thmin": 0.0, "thmax": 0.0, "type": "Nom"}, "14": {"size": 27.0, "dimin": 28.0, "dimax": 0.0, "domin": 60.0, "domax": 0.0, "thnom": 10.0, "thmin": 0.0, "thmax": 0.0, "type": "Nom"}, "15": {"size": 30.0, "dimin": 31.0, "dimax": 0.0, "domin": 68.0, "domax": 0.0, "thnom": 10.0, "thmin": 0.0, "thmax": 0.0, "type": "Nom"}}, "6796": {"1": {"size": 2.0, "dimin": 2.2, "dimax": 0.0, "domin": 5.0, "domax": 0.0, "thnom": 0.4, "thmin": 0.0, "thmax": 0.0, "type": "Nom"}, "2": {"size": 2.5, "dimin": 2.7, "dimax": 0.0, "domin": 6.0, "domax": 0.0, "thnom": 0.5, "thmin": 0.0, "thmax": 0.0, "type": "Nom"}, "3": {"size": 3.0, "dimin": 3.2, "dimax": 0.0, "domin": 7.0, "domax": 0.0, "thnom": 0.6, "thmin": 0.0, "thmax": 0.0, "type": "Nom"}, "4": {"size": 3.5, "dimin": 3.7, "dimax": 0.0, "domin": 8.0, "domax": 0.0, "thnom": 0.8, "thmin": 0.0, "thmax": 0.0, "type": "Nom"}, "5": {"size": 4.0, "dimin": 4.3, "dimax": 0.0, "domin": 9.0, "domax": 0.0, "thnom": 1.0, "thmin": 0.0, "thmax": 0.0, "type": "Nom"}, "6": {"size": 5.0, "dimin": 5.3, "dimax": 0.0, "domin": 11.0, "domax": 0.0, "thnom": 1.2, "thmin": 0.0, "thmax": 0.0, "type": "Nom"}, "7": {"size": 6.0, "dimin": 6.4, "dimax": 0.0, "domin": 14.0, "domax": 0.0, "thnom": 1.5, "thmin": 0.0, "thmax": 0.0, "type": "Nom"}, "8": {"size": 7.0, "dimin": 7.4, "dimax": 0.0, "domin": 17.0, "domax": 0.0, "thnom": 1.75, "thmin": 0.0, "thmax": 0.0, "type": "Nom"}, "9": {"size": 8.0, "dimin": 8.4, "dimax": 0.0, "domin": 18.0, "domax": 0.0, "thnom": 2.0, "thmin": 0.0, "thmax": 0.0, "type": "Nom"}, "10": {"size": 10.0, "dimin": 10.5, "dimax": 0.0, "domin": 23.0, "domax": 0.0, "thnom": 2.5, "thmin": 0.0, "thmax": 0.0, "type": "Nom"}, "11": {"size": 12.0, "dimin": 13.0, "dimax": 0.0, "domin": 29.0, "domax": 0.0, "thnom": 3.0, "thmin": 0.0, "thmax": 0.0, "type": "Nom"}, "12": {"size": 14.0, "dimin": 15.0, "dimax": 0.0, "domin": 35.0, "domax": 0.0, "thnom": 3.5, "thmin": 0.0, "thmax": 0.0, "type": "Nom"}, "13": {"size": 16.0, "dimin": 17.0, "dimax": 0.0, "domin": 39.0, "domax": 0.0, "thnom": 4.0, "thmin": 0.0, "thmax": 0.0, "type": "Nom"}, "14": {"size": 18.0, "dimin": 19.0, "dimax": 0.0, "domin": 42.0, "domax": 0.0, "thnom": 4.5, "thmin": 0.0, "thmax": 0.0, "type": "Nom"}, "15": {"size": 20.0, "dimin": 21.0, "dimax": 0.0, "domin": 45.0, "domax": 0.0, "thnom": 5.0, "thmin": 0.0, "thmax": 0.0, "type": "Nom"}, "16": {"size": 22.0, "dimin": 23.0, "dimax": 0.0, "domin": 49.0, "domax": 0.0, "thnom": 5.5, "thmin": 0.0, "thmax": 0.0, "type": "Nom"}, "17": {"size": 24.0, "dimin": 24.0, "dimax": 0.0, "domin": 56.0, "domax": 0.0, "thnom": 6.0, "thmin": 0.0, "thmax": 0.0, "type": "Nom"}, "18": {"size": 27.0, "dimin": 28.0, "dimax": 0.0, "domin": 60.0, "domax": 0.0, "thnom": 6.5, "thmin": 0.0, "thmax": 0.0, "type": "Nom"}, "19": {"size": 30.0, "dimin": 31.0, "dimax": 0.0, "domin": 70.0, "domax": 0.0, "thnom": 7.0, "thmin": 0.0, "thmax": 0.0, "type": "Nom"}}, "25-510": {"1": {"size": 5.0, "dimin": 5.3, "dimax": 5.6, "domin": 11.0, "domax": 10.57, "thnom": 1.2, "thmin": 1.16, "thmax": 1.24, "type": "A"}, "2": {"size": 5.0, "dimin": 5.3, "dimax": 5.6, "domin": 15.0, "domax": 14.57, "thnom": 1.4, "thmin": 1.3599999999999999, "thmax": 1.44, "type": "B"}, "3": {"size": 6.0, "dimin": 6.4, "dimax": 6.76, "domin": 12.0, "domax": 11.57, "thnom": 1.4, "thmin": 1.3599999999999999, "thmax": 1.44, "type": "Min"}, "4": {"size": 6.0, "dimin": 6.4, "dimax": 6.76, "domin": 14.0, "domax": 13.57, "thnom": 1.5, "thmin": 1.45, "thmax": 1.55, "type": "Nom"}, "5": {"size": 6.0, "dimin": 6.4, "dimax": 6.76, "domin": 18.0, "domax": 17.57, "thnom": 1.7, "thmin": 1.65, "thmax": 1.75, "type": "Max"}, "6": {"size": 8.0, "dimin": 8.4, "dimax": 8.76, "domin": 16.0, "domax": 15.57, "thnom": 1.9, "thmin": 1.8499999999999999, "thmax": 1.95, "type": "Min"}, "7": {"size": 8.0, "dimin": 8.4, "dimax": 8.76, "domin": 18.0, "domax": 17.57, "thnom": 2.0, "thmin": 1.95, "thmax": 2.05, "type": "Nom"}, "8": {"size": 8.0, "dimin": 8.4, "dimax": 8.76, "domin": 22.0, "domax": 21.48, "thnom": 2.2, "thmin": 2.1500000000000004, "thmax": 2.25, "type": "Max"}, "9": {"size": 10.0, "dimin": 10.5, "dimax": 10.93, "domin": 20.0, "domax": 19.48, "thnom": 2.2, "thmin": 2.1500000000000004, "thmax": 2.25, "type": "Min"}, "10": {"size": 10.0, "dimin": 10.5, "dimax": 10.93, "domin": 22.0, "domax": 21.48, "thnom": 2.4, "thmin": 2.35, "thmax": 2.4499999999999997, "type": "Nom"}, "11": {"size": 10.0, "dimin": 10.5, "dimax": 10.93, "domin": 27.0, "domax": 26.48, "thnom": 2.8, "thmin": 2.7399999999999998, "thmax": 2.86, "type": "Max"}, "12": {"size": 12.0, "dimin": 13.0, "dimax": 13.43, "domin": 24.0, "domax": 23.48, "thnom": 2.8, "thmin": 2.7399999999999998, "thmax": 2.86, "type": "A"}, "13": {"size": 12.0, "dimin": 13.0, "dimax": 13.43, "domin": 30.0, "domax": 29.48, "thnom": 3.2, "thmin": 3.14, "thmax": 3.2600000000000002, "type": "B"}, "14": {"size": 14.0, "dimin": 15.0, "dimax": 15.43, "domin": 28.0, "domax": 27.48, "thnom": 3.0, "thmin": 2.94, "thmax": 3.06, "type": "Nom"}, "15": {"size": 16.0, "dimin": 17.0, "dimax": 17.43, "domin": 32.0, "domax": 31.5, "thnom": 3.4, "thmin": 3.33, "thmax": 3.4699999999999998, "type": "A"}, "16": {"size": 16.0, "dimin": 17.0, "dimax": 17.43, "domin": 39.0, "domax": 38.5, "thnom": 3.6, "thmin": 3.5300000000000002, "thmax": 3.67, "type": "B"}, "17": {"size": 20.0, "dimin": 21.0, "dimax": 21.52, "domin": 38.0, "domax": 37.5, "thnom": 4.0, "thmin": 3.93, "thmax": 4.07, "type": "A"}, "18": {"size": 20.0, "dimin": 21.0, "dimax": 21.52, "domin": 45.0, "domax": 44.5, "thnom": 4.4, "thmin": 4.33, "thmax": 4.470000000000001, "type": "B"}}, "25-511": {"1": {"size": 3.0, "dimin": 3.1, "dimax": 3.35, "domin": 6.24, "domax": 5.76, "thnom": 0.5, "thmin": 0.47, "thmax": 0.53, "type": "Min"}, "2": {"size": 3.0, "dimin": 3.1, "dimax": 3.35, "domin": 8.29, "domax": 7.71, "thnom": 0.6, "thmin": 0.57, "thmax": 0.63, "type": "Nom"}, "3": {"size": 3.0, "dimin": 3.1, "dimax": 3.35, "domin": 10.29, "domax": 9.71, "thnom": 0.6, "thmin": 0.57, "thmax": 0.63, "type": "Max"}, "4": {"size": 4.0, "dimin": 4.1, "dimax": 4.4, "domin": 8.29, "domax": 7.71, "thnom": 0.8, "thmin": 0.77, "thmax": 0.8300000000000001, "type": "Min"}, "5": {"size": 4.0, "dimin": 4.1, "dimax": 4.4, "domin": 10.29, "domax": 9.71, "thnom": 0.9, "thmin": 0.86, "thmax": 0.9400000000000001, "type": "Nom"}, "6": {"size": 4.0, "dimin": 4.1, "dimax": 4.4, "domin": 14.35, "domax": 13.65, "thnom": 1.0, "thmin": 0.96, "thmax": 1.04, "type": "Max"}, "7": {"size": 5.0, "dimin": 5.1, "dimax": 5.4, "domin": 10.29, "domax": 9.71, "thnom": 1.0, "thmin": 0.96, "thmax": 1.04, "type": "Min"}, "8": {"size": 5.0, "dimin": 5.1, "dimax": 5.4, "domin": 12.35, "domax": 11.65, "thnom": 1.1, "thmin": 1.06, "thmax": 1.1400000000000001, "type": "Nom"}, "9": {"size": 5.0, "dimin": 5.1, "dimax": 5.4, "domin": 16.35, "domax": 15.65, "thnom": 1.2, "thmin": 1.16, "thmax": 1.24, "type": "Max"}, "10": {"size": 6.0, "dimin": 6.1, "dimax": 6.4, "domin": 12.35, "domax": 11.65, "thnom": 1.2, "thmin": 1.16, "thmax": 1.24, "type": "Min"}, "11": {"size": 6.0, "dimin": 6.1, "dimax": 6.4, "domin": 14.35, "domax": 13.65, "thnom": 1.3, "thmin": 1.26, "thmax": 1.34, "type": "Nom"}, "12": {"size": 6.0, "dimin": 6.1, "dimax": 6.4, "domin": 18.35, "domax": 17.65, "thnom": 1.4, "thmin": 1.3599999999999999, "thmax": 1.44, "type": "Max"}, "13": {"size": 8.0, "dimin": 8.2, "dimax": 8.56, "domin": 16.35, "domax": 15.65, "thnom": 1.4, "thmin": 1.3599999999999999, "thmax": 1.44, "type": "Min"}, "14": {"size": 8.0, "dimin": 8.2, "dimax": 8.56, "domin": 18.35, "domax": 17.65, "thnom": 1.4, "thmin": 1.3599999999999999, "thmax": 1.44, "type": "Nom"}, "15": {"size": 8.0, "dimin": 8.2, "dimax": 8.56, "domin": 22.42, "domax": 21.58, "thnom": 1.6, "thmin": 1.55, "thmax": 1.6500000000000001, "type": "Max"}, "16": {"size": 10.0, "dimin": 10.2, "dimax": 10.56, "domin": 20.42, "domax": 19.58, "thnom": 1.6, "thmin": 1.55, "thmax": 1.6500000000000001, "type": "Min"}, "17": {"size": 10.0, "dimin": 10.2, "dimax": 10.56, "domin": 22.42, "domax": 21.58, "thnom": 1.6, "thmin": 1.55, "thmax": 1.6500000000000001, "type": "Nom"}, "18": {"size": 10.0, "dimin": 10.2, "dimax": 10.56, "domin": 27.42, "domax": 26.58, "thnom": 1.8, "thmin": 1.75, "thmax": 1.85, "type": "Max"}, "19": {"size": 12.0, "dimin": 12.4, "dimax": 12.83, "domin": 24.42, "domax": 23.58, "thnom": 1.8, "thmin": 1.75, "thmax": 1.85, "type": "Min"}, "20": {"size": 12.0, "dimin": 12.4, "dimax": 12.83, "domin": 27.42, "domax": 26.58, "thnom": 1.8, "thmin": 1.75, "thmax": 1.85, "type": "Nom"}, "21": {"size": 12.0, "dimin": 12.4, "dimax": 12.83, "domin": 32.5, "domax": 31.5, "thnom": 2.0, "thmin": 1.95, "thmax": 2.05, "type": "Max"}, "22": {"size": 14.0, "dimin": 14.4, "dimax": 14.83, "domin": 30.42, "domax": 29.58, "thnom": 2.4, "thmin": 2.34, "thmax": 2.46, "type": "Nom"}, "23": {"size": 16.0, "dimin": 16.4, "dimax": 16.83, "domin": 32.5, "domax": 31.5, "thnom": 2.8, "thmin": 2.7399999999999998, "thmax": 2.86, "type": "Nom"}, "24": {"size": 20.0, "dimin": 20.5, "dimax": 21.02, "domin": 40.5, "domax": 39.5, "thnom": 3.2, "thmin": 3.14, "thmax": 3.2600000000000002, "type": "Nom"}}, "4027": {"1": {"size": "M1.6", "dia": 1.6, "pitch": 0.35, "dw": 0.4, "k": 0.0}, "2": {"size": "M2", "dia": 2.0, "pitch": 0.4, "dw": 0.5, "k": 0.0}, "3": {"size": "M2.5", "dia": 2.5, "pitch": 0.45, "dw": 0.65, "k": 0.0}, "4": {"size": "M3", "dia": 3.0, "pitch": 0.5, "dw": 0.75, "k": 0.0}, "5": {"size": "M4", "dia": 4.0, "pitch": 0.7, "dw": 1.0, "k": 0.0}, "6": {"size": "M5", "dia": 5.0, "pitch": 0.8, "dw": 1.25, "k": 0.0}, "7": {"size": "M6", "dia": 6.0, "pitch": 1.0, "dw": 1.5, "k": 0.0}, "8": {"size": "M8", "dia": 8.0, "pitch": 1.25, "dw": 2.0, "k": 0.0}, "9": {"size": "M10", "dia": 10.0, "pitch": 1.5, "dw": 2.5, "k": 0.0}, "10": {"size": "M12", "dia": 12.0, "pitch": 1.75, "dw": 3.0, "k": 0.0}, "11": {"size": "M16", "dia": 16.0, "pitch": 2.0, "dw": 4.0, "k": 0.0}, "12": {"size": "M20", "dia": 20.0, "pitch": 2.5, "dw": 5.0, "k": 0.0}, "13": {"size": "M24", "dia": 24.0, "pitch": 3.0, "dw": 6.0, "k": 0.0}}, "4029": {"1": {"size": "M1.6", "dia": 1.6, "pitch": 0.35, "dw": 0.55, "k": 0.0}, "2": {"size": "M2", "dia": 2.0, "pitch": 0.4, "dw": 0.75, "k": 0.0}, "3": {"size": "M2.5", "dia": 2.5, "pitch": 0.45, "dw": 0.95, "k": 0.0}, "4": {"size": "M3", "dia": 3.0, "pitch": 0.5, "dw": 1.15, "k": 0.0}, "5": {"size": "M4", "dia": 4.0, "pitch": 0.7, "dw": 1.75, "k": 0.0}, "6": {"size": "M5", "dia": 5.0, "pitch": 0.8, "dw": 2.25, "k": 0.0}, "7": {"size": "M6", "dia": 6.0, "pitch": 1.0, "dw": 2.75, "k": 0.0}, "8": {"size": "M8", "dia": 8.0, "pitch": 1.25, "dw": 4.7, "k": 0.0}, "9": {"size": "M10", "dia": 10.0, "pitch": 1.5, "dw": 5.7, "k": 0.0}, "10": {"size": "M12", "dia": 12.0, "pitch": 1.75, "dw": 7.64, "k": 0.0}, "11": {"size": "M16", "dia": 16.0, "pitch": 2.0, "dw": 9.64, "k": 0.0}, "12": {"size": "M20", "dia": 20.0, "pitch": 2.5, "dw": 13.57, "k": 0.0}, "13": {"size": "M24", "dia": 24.0, "pitch": 3.0, "dw": 15.57, "k": 0.0}}, "14584": {"1": {"size": "M2", "dia": 2.0, "pitch": 0.4, "dw": 3.5, "k": 0.5}, "2": {"size": "M2.5", "dia": 2.5, "pitch": 0.45, "dw": 4.4, "k": 0.6}, "3": {"size": "M3", "dia": 3.0, "pitch": 0.5, "dw": 5.2, "k": 0.8}, "4": {"size": "M3.5", "dia": 3.5, "pitch": 0.6, "dw": 6.94, "k": 0.9}, "5": {"size": "M4", "dia": 4.0, "pitch": 0.7, "dw": 8.04, "k": 1.0}, "6": {"size": "M5", "dia": 5.0, "pitch": 0.8, "dw": 8.94, "k": 1.3}, "7": {"size": "M6", "dia": 6.0, "pitch": 1.0, "dw": 10.87, "k": 1.5}, "8": {"size": "M8", "dia": 8.0, "pitch": 1.25, "dw": 15.37, "k": 2.0}, "9": {"size": "M10", "dia": 10.0, "pitch": 1.5, "dw": 17.78, "k": 2.5}}, "7047": {"1": {"size": "M1.6", "dia": 1.6, "pitch": 0.35, "dw": 2.7, "k": 1.0}, "2": {"size": "M2", "dia": 2.0, "pitch": 0.4, "dw": 3.5, "k": 1.2}, "3": {"size": "M2.5", "dia": 2.5, "pitch": 0.45, "dw": 4.4, "k": 1.5}, "4": {"size": "M3", "dia": 3.0, "pitch": 0.5, "dw": 5.2, "k": 1.65}, "5": {"size": "M3.5", "dia": 3.5, "pitch": 0.6, "dw": 6.94, "k": 2.35}, "6": {"size": "M4", "dia": 4.0, "pitch": 0.7, "dw": 8.04, "k": 2.7}, "7": {"size": "M5", "dia": 5.0, "pitch": 0.8, "dw": 8.94, "k": 2.7}, "8": {"size": "M6", "dia": 6.0, "pitch": 1.0, "dw": 10.87, "k": 3.3}, "9": {"size": "M8", "dia": 8.0, "pitch": 1.25, "dw": 15.37, "k": 4.65}, "10": {"size": "M10", "dia": 10.0, "pitch": 1.5, "dw": 17.78, "k": 5.0}}, "7046-2": {"1": {"size": "M2", "dia": 2.0, "pitch": 0.4, "dw": 3.5, "k": 1.2}, "2": {"size": "M2.5", "dia": 2.5, "pitch": 0.45, "dw": 4.4, "k": 1.5}, "3": {"size": "M3", "dia": 3.0, "pitch": 0.5, "dw": 5.2, "k": 1.65}, "4": {"size": "M3.5", "dia": 3.5, "pitch": 0.6, "dw": 6.9, "k": 2.35}, "5": {"size": "M4", "dia": 4.0, "pitch": 0.7, "dw": 8.0, "k": 2.7}, "6": {"size": "M5", "dia": 5.0, "pitch": 0.8, "dw": 8.9, "k": 2.7}, "7": {"size": "M6", "dia": 6.0, "pitch": 1.0, "dw": 10.9, "k": 3.3}, "8": {"size": "M8", "dia": 8.0, "pitch": 1.25, "dw": 15.4, "k": 4.65}, "9": {"size": "M10", "dia": 10.0, "pitch": 1.5, "dw": 17.8, "k": 5.0}}, "7380": {"1": {"size": "M3", "dia": 3.0, "pitch": 0.5, "dw": 5.0, "k": 1.4}, "2": {"size": "M4", "dia": 4.0, "pitch": 0.7, "dw": 6.84, "k": 1.95}, "3": {"size": "M5", "dia": 5.0, "pitch": 0.8, "dw": 8.74, "k": 2.5}, "4": {"size": "M6", "dia": 6.0, "pitch": 1.0, "dw": 9.57, "k": 3.0}, "5": {"size": "M8", "dia": 8.0, "pitch": 1.25, "dw": 13.07, "k": 4.1}, "6": {"size": "M10", "dia": 10.0, "pitch": 1.5, "dw": 16.57, "k": 5.2}, "7": {"size": "M12", "dia": 12.0, "pitch": 1.75, "dw": 19.68, "k": 6.24}, "8": {"size": "M16", "dia": 16.0, "pitch": 2.0, "dw": 26.68, "k": 8.44}}, "10642": {"1": {"size": "M3", "dia": 3.0, "pitch": 0.5, "dw": 5.54, "k": 1.86}, "2": {"size": "M4", "dia": 4.0, "pitch": 0.7, "dw": 7.53, "k": 2.48}, "3": {"size": "M5", "dia": 5.0, "pitch": 0.8, "dw": 9.43, "k": 3.1}, "4": {"size": "M6", "dia": 6.0, "pitch": 1.0, "dw": 11.34, "k": 3.72}, "5": {"size": "M8", "dia": 8.0, "pitch": 1.25, "dw": 15.24, "k": 4.96}, "6": {"size": "M10", "dia": 10.0, "pitch": 1.5, "dw": 19.22, "k": 6.2}, "7": {"size": "M12", "dia": 12.0, "pitch": 1.75, "dw": 23.12, "k": 7.44}, "8": {"size": "M14", "dia": 14.0, "pitch": 2.0, "dw": 26.52, "k": 8.4}, "9": {"size": "M16", "dia": 16.0, "pitch": 2.0, "dw": 29.01, "k": 8.8}, "10": {"size": "M20", "dia": 20.0, "pitch": 2.5, "dw": 35.4, "k": 10.16}}, "14581": {"1": {"size": "M2", "dia": 2.0, "pitch": 0.4, "dw": 3.5, "k": 1.2}, "2": {"size": "M2.5", "dia": 2.5, "pitch": 0.45, "dw": 4.4, "k": 1.5}, "3": {"size": "M3", "dia": 3.0, "pitch": 0.5, "dw": 5.2, "k": 1.65}, "4": {"size": "M3.5", "dia": 3.5, "pitch": 0.6, "dw": 6.94, "k": 2.35}, "5": {"size": "M4", "dia": 4.0, "pitch": 0.7, "dw": 8.04, "k": 2.7}, "6": {"size": "M5", "dia": 5.0, "pitch": 0.8, "dw": 8.94, "k": 2.7}, "7": {"size": "M6", "dia": 6.0, "pitch": 1.0, "dw": 10.87, "k": 3.3}, "8": {"size": "M8", "dia": 8.0, "pitch": 1.25, "dw": 15.37, "k": 4.65}, "9": {"size": "M10", "dia": 10.0, "pitch": 1.5, "dw": 17.78, "k": 5.0}}, "7984": {"1": {"size": "M3", "dia": 3.0, "pitch": 0.5, "dw": 4.84, "k": 1.86}, "2": {"size": "M4", "dia": 4.0, "pitch": 0.7, "dw": 6.2, "k": 2.66}, "3": {"size": "M5", "dia": 5.0, "pitch": 0.8, "dw": 7.7, "k": 3.32}, "4": {"size": "M6", "dia": 6.0, "pitch": 1.0, "dw": 9.2, "k": 3.82}, "5": {"size": "M8", "dia": 8.0, "pitch": 1.25, "dw": 12.03, "k": 4.82}, "6": {"size": "M10", "dia": 10.0, "pitch": 1.5, "dw": 15.03, "k": 5.82}, "7": {"size": "M12", "dia": 12.0, "pitch": 1.75, "dw": 17.03, "k": 6.78}, "8": {"size": "M14", "dia": 14.0, "pitch": 2.0, "dw": 19.83, "k": 7.78}, "9": {"size": "M16", "dia": 16.0, "pitch": 2.0, "dw": 22.83, "k": 8.78}, "10": {"size": "M18", "dia": 18.0, "pitch": 2.5, "dw": 25.83, "k": 9.78}, "11": {"size": "M20", "dia": 20.0, "pitch": 2.5, "dw": 28.83, "k": 10.73}, "12": {"size": "M22", "dia": 22.0, "pitch": 2.5, "dw": 31.61, "k": 11.73}, "13": {"size": "M24", "dia": 24.0, "pitch": 3.0, "dw": 34.61, "k": 12.73}}, "4762": {"1": {"size": "M1.6", "dia": 1.6, "pitch": 0.35, "dw": 2.72, "k": 1.46}, "2": {"size": "M2", "dia": 2.0, "pitch": 0.4, "dw": 3.48, "k": 1.86}, "3": {"size": "M2.5", "dia": 2.5, "pitch": 0.45, "dw": 4.18, "k": 2.36}, "4": {"size": "M3", "dia": 3.0, "pitch": 0.5, "dw": 5.07, "k": 2.86}, "5": {"size": "M4", "dia": 4.0, "pitch": 0.7, "dw": 6.53, "k": 3.82}, "6": {"size": "M5", "dia": 5.0, "pitch": 0.8, "dw": 8.3, "k": 4.82}, "7": {"size": "M6", "dia": 6.0, "pitch": 1.0, "dw": 9.38, "k": 5.7}, "8": {"size": "M8", "dia": 8.0, "pitch": 1.25, "dw": 12.33, "k": 7.64}, "9": {"size": "M10", "dia": 10.0, "pitch": 1.5, "dw": 15.33, "k": 9.64}, "10": {"size": "M12", "dia": 12.0, "pitch": 1.75, "dw": 17.23, "k": 11.57}, "11": {"size": "M14", "dia": 14.0, "pitch": 2.0, "dw": 20.17, "k": 13.57}, "12": {"size": "M16", "dia": 16.0, "pitch": 2.0, "dw": 23.17, "k": 15.57}, "13": {"size": "M20", "dia": 20.0, "pitch": 2.5, "dw": 28.87, "k": 19.48}, "14": {"size": "M24", "dia": 24.0, "pitch": 3.0, "dw": 34.81, "k": 23.48}, "15": {"size": "M30", "dia": 30.0, "pitch": 3.5, "dw": 43.61, "k": 29.48}, "16": {"size": "M36", "dia": 36.0, "pitch": 4.0, "dw": 52.54, "k": 35.38}, "17": {"size": "M42", "dia": 42.0, "pitch": 4.5, "dw": 61.34, "k": 41.38}, "18": {"size": "M48", "dia": 48.0, "pitch": 5.0, "dw": 70.34, "k": 47.38}, "19": {"size": "M56", "dia": 56.0, "pitch": 5.5, "dw": 82.26, "k": 55.26}, "20": {"size": "M64", "dia": 64.0, "pitch": 6.0, "dw": 94.26, "k": 63.26}}, "4014": {"1": {"size": "M1.6", "dia": 1.6, "pitch": 0.35, "dw": 2.27, "k": 0.975}, "2": {"size": "M2", "dia": 2.0, "pitch": 0.4, "dw": 3.07, "k": 1.275}, "3": {"size": "M2.5", "dia": 2.5, "pitch": 0.45, "dw": 4.07, "k": 1.575}, "4": {"size": "M3", "dia": 3.0, "pitch": 0.5, "dw": 4.57, "k": 1.875}, "5": {"size": "M4", "dia": 4.0, "pitch": 0.7, "dw": 5.88, "k": 2.675}, "6": {"size": "M5", "dia": 5.0, "pitch": 0.8, "dw": 6.88, "k": 3.35}, "7": {"size": "M6", "dia": 6.0, "pitch": 1.0, "dw": 8.88, "k": 3.85}, "8": {"size": "M8", "dia": 8.0, "pitch": 1.25, "dw": 11.63, "k": 5.15}, "9": {"size": "M10", "dia": 10.0, "pitch": 1.5, "dw": 14.63, "k": 6.22}, "10": {"size": "M12", "dia": 12.0, "pitch": 1.75, "dw": 16.63, "k": 7.32}, "11": {"size": "M16", "dia": 16.0, "pitch": 2.0, "dw": 22.49, "k": 9.82}, "12": {"size": "M20", "dia": 20.0, "pitch": 2.5, "dw": 28.19, "k": 12.285}, "13": {"size": "M24", "dia": 24.0, "pitch": 3.0, "dw": 33.61, "k": 14.785}, "14": {"size": "M30", "dia": 30.0, "pitch": 3.5, "dw": "NA", "k": "NA"}, "15": {"size": "M36", "dia": 36.0, "pitch": 4.0, "dw": "NA", "k": "NA"}, "16": {"size": "M42", "dia": 42.0, "pitch": 4.5, "dw": "NA", "k": "NA"}, "17": {"size": "M48", "dia": 48.0, "pitch": 5.0, "dw": "NA", "k": "NA"}, "18": {"size": "M56", "dia": 56.0, "pitch": 5.5, "dw": "NA", "k": "NA"}, "19": {"size": "M64", "dia": 64.0, "pitch": 6.0, "dw": "NA", "k": "NA"}}, "603": {"1": {"size": "M5", "dia": 5.0, "pitch": 0.8, "dw": 12.45, "k": 2.7}, "2": {"size": "M6", "dia": 6.0, "pitch": 1.0, "dw": 15.45, "k": 3.12}, "3": {"size": "M8", "dia": 8.0, "pitch": 1.25, "dw": 19.35, "k": 4.12}, "4": {"size": "M10", "dia": 10.0, "pitch": 1.5, "dw": 23.35, "k": 4.62}, "5": {"size": "M12", "dia": 12.0, "pitch": 1.75, "dw": 29.35, "k": 6.05}, "6": {"size": "M16", "dia": 16.0, "pitch": 2.0, "dw": 37.2, "k": 8.05}, "7": {"size": "M20", "dia": 20.0, "pitch": 2.5, "dw": 45.2, "k": 9.95}}, "4017": {"1": {"size": "M1.6", "dia": 1.6, "pitch": 0.35, "dw": 2.27, "k": 0.975}, "2": {"size": "M2", "dia": 2.0, "pitch": 0.4, "dw": 3.07, "k": 1.275}, "3": {"size": "M2.5", "dia": 2.5, "pitch": 0.45, "dw": 4.07, "k": 1.575}, "4": {"size": "M3", "dia": 3.0, "pitch": 0.5, "dw": 4.57, "k": 1.875}, "5": {"size": "M4", "dia": 4.0, "pitch": 0.7, "dw": 5.88, "k": 2.675}, "6": {"size": "M5", "dia": 5.0, "pitch": 0.8, "dw": 6.88, "k": 3.35}, "7": {"size": "M6", "dia": 6.0, "pitch": 1.0, "dw": 8.88, "k": 3.85}, "8": {"size": "M8", "dia": 8.0, "pitch": 1.25, "dw": 11.63, "k": 5.15}, "9": {"size": "M10", "dia": 10.0, "pitch": 1.5, "dw": 14.63, "k": 6.22}, "10": {"size": "M12", "dia": 12.0, "pitch": 1.75, "dw": 16.63, "k": 7.32}, "11": {"size": "M16", "dia": 16.0, "pitch": 2.0, "dw": 22.49, "k": 9.82}, "12": {"size": "M20", "dia": 20.0, "pitch": 2.5, "dw": 28.19, "k": 12.285}, "13": {"size": "M24", "dia": 24.0, "pitch": 3.0, "dw": 33.61, "k": 14.785}, "14": {"size": "M30", "dia": 30.0, "pitch": 3.5, "dw": "NA", "k": "NA"}, "15": {"size": "M36", "dia": 36.0, "pitch": 4.0, "dw": "NA", "k": "NA"}, "16": {"size": "M42", "dia": 42.0, "pitch": 4.5, "dw": "NA", "k": "NA"}, "17": {"size": "M48", "dia": 48.0, "pitch": 5.0, "dw": "NA", "k": "NA"}, "18": {"size": "M56", "dia": 56.0, "pitch": 5.5, "dw": "NA", "k": "NA"}, "19": {"size": "M64", "dia": 64.0, "pitch": 6.0, "dw": "NA", "k": "NA"}}, "4032": {"1": {"size": 1.6, "damax": 1.84, "damin": 1.6, "dw": 2.4, "m": 1.05}, "2": {"size": 2.0, "damax": 2.3, "damin": 2.0, "dw": 3.1, "m": 1.35}, "3": {"size": 2.5, "damax": 2.9, "damin": 2.5, "dw": 4.1, "m": 1.75}, "4": {"size": 3.0, "damax": 3.45, "damin": 3.0, "dw": 4.6, "m": 2.15}, "5": {"size": 4.0, "damax": 4.6, "damin": 4.0, "dw": 5.9, "m": 2.9}, "6": {"size": 5.0, "damax": 5.75, "damin": 5.0, "dw": 6.9, "m": 4.4}, "7": {"size": 6.0, "damax": 6.75, "damin": 6.0, "dw": 8.9, "m": 4.9}, "8": {"size": 8.0, "damax": 8.75, "damin": 8.0, "dw": 11.6, "m": 6.44}, "9": {"size": 10.0, "damax": 10.8, "damin": 10.0, "dw": 14.6, "m": 8.04}, "10": {"size": 12.0, "damax": 13.0, "damin": 12.0, "dw": 16.6, "m": 10.37}, "11": {"size": 16.0, "damax": 17.3, "damin": 16.0, "dw": 22.5, "m": 14.1}, "12": {"size": 20.0, "damax": 21.6, "damin": 20.0, "dw": 27.7, "m": 16.9}, "13": {"size": 24.0, "damax": 25.9, "damin": 24.0, "dw": 33.3, "m": 20.2}, "14": {"size": 30.0, "damax": 32.4, "damin": 30.0, "dw": 42.8, "m": 24.3}, "15": {"size": 36.0, "damax": 38.9, "damin": 36.0, "dw": 51.1, "m": 29.4}, "16": {"size": 42.0, "damax": 45.4, "damin": 42.0, "dw": 60.0, "m": 32.4}, "17": {"size": 48.0, "damax": 51.8, "damin": 48.0, "dw": 69.5, "m": 36.4}, "18": {"size": 56.0, "damax": 60.5, "damin": 56.0, "dw": 78.7, "m": 43.4}, "19": {"size": 64.0, "damax": 69.1, "damin": 64.0, "dw": 88.2, "m": 49.1}}, "4035": {"1": {"size": 1.6, "damax": 1.84, "damin": 1.6, "dw": 2.4, "m": 0.75}, "2": {"size": 2.0, "damax": 2.3, "damin": 2.0, "dw": 3.1, "m": 0.95}, "3": {"size": 2.5, "damax": 2.9, "damin": 2.5, "dw": 4.1, "m": 1.35}, "4": {"size": 3.0, "damax": 3.45, "damin": 3.0, "dw": 4.6, "m": 1.55}, "5": {"size": 4.0, "damax": 4.6, "damin": 4.0, "dw": 5.9, "m": 1.95}, "6": {"size": 5.0, "damax": 5.75, "damin": 5.0, "dw": 6.9, "m": 2.45}, "7": {"size": 6.0, "damax": 6.75, "damin": 6.0, "dw": 8.9, "m": 2.9}, "8": {"size": 8.0, "damax": 8.75, "damin": 8.0, "dw": 11.6, "m": 3.7}, "9": {"size": 10.0, "damax": 10.8, "damin": 10.0, "dw": 14.6, "m": 4.7}, "10": {"size": 12.0, "damax": 13.0, "damin": 12.0, "dw": 16.6, "m": 5.7}, "11": {"size": 16.0, "damax": 17.3, "damin": 16.0, "dw": 22.5, "m": 7.42}, "12": {"size": 20.0, "damax": 21.6, "damin": 20.0, "dw": 27.7, "m": 9.1}, "13": {"size": 24.0, "damax": 25.9, "damin": 24.0, "dw": 33.2, "m": 10.9}, "14": {"size": 30.0, "damax": 32.4, "damin": 30.0, "dw": 42.8, "m": 13.9}, "15": {"size": 36.0, "damax": 38.9, "damin": 36.0, "dw": 51.1, "m": 16.9}, "16": {"size": 42.0, "damax": 45.4, "damin": 42.0, "dw": 60.0, "m": 19.7}, "17": {"size": 48.0, "damax": 51.8, "damin": 48.0, "dw": 69.5, "m": 22.7}, "18": {"size": 56.0, "damax": 60.5, "damin": 56.0, "dw": 78.7, "m": 26.7}, "19": {"size": 64.0, "damax": 69.1, "damin": 64.0, "dw": 88.2, "m": 30.4}}, "7040": {"1": {"size": 3.0, "damax": 3.45, "damin": 3.0, "dw": 4.57, "m": 2.15}, "2": {"size": 4.0, "damax": 4.6, "damin": 4.0, "dw": 5.88, "m": 2.9}, "3": {"size": 5.0, "damax": 5.75, "damin": 5.0, "dw": 6.88, "m": 4.4}, "4": {"size": 6.0, "damax": 6.75, "damin": 6.0, "dw": 8.88, "m": 4.9}, "5": {"size": 8.0, "damax": 8.75, "damin": 8.0, "dw": 11.63, "m": 6.44}, "6": {"size": 10.0, "damax": 10.8, "damin": 10.0, "dw": 14.63, "m": 8.04}, "7": {"size": 12.0, "damax": 13.0, "damin": 12.0, "dw": 16.63, "m": 10.37}, "8": {"size": 14.0, "damax": 15.1, "damin": 14.0, "dw": 19.64, "m": 12.1}, "9": {"size": 16.0, "damax": 17.3, "damin": 16.0, "dw": 22.49, "m": 14.1}, "10": {"size": 20.0, "damax": 21.6, "damin": 20.0, "dw": 27.7, "m": 16.9}, "11": {"size": 24.0, "damax": 25.9, "damin": 24.0, "dw": 33.25, "m": 20.2}, "12": {"size": 30.0, "damax": 32.4, "damin": 30.0, "dw": 42.75, "m": 24.3}, "13": {"size": 36.0, "damax": 38.9, "damin": 36.0, "dw": 51.11, "m": 29.4}}, "7042": {"1": {"size": 5.0, "damax": 5.75, "damin": 5.0, "dw": 6.88, "m": 3.52}, "2": {"size": 6.0, "damax": 6.75, "damin": 6.0, "dw": 8.88, "m": 3.92}, "3": {"size": 8.0, "damax": 8.75, "damin": 8.0, "dw": 11.63, "m": 5.15}, "4": {"size": 10.0, "damax": 10.8, "damin": 10.0, "dw": 14.63, "m": 6.43}, "5": {"size": 12.0, "damax": 13.0, "damin": 12.0, "dw": 16.63, "m": 8.3}, "6": {"size": 14.0, "damax": 15.1, "damin": 14.0, "dw": 19.64, "m": 9.68}, "7": {"size": 16.0, "damax": 17.3, "damin": 16.0, "dw": 22.49, "m": 11.28}, "8": {"size": 20.0, "damax": 21.6, "damin": 20.0, "dw": 27.7, "m": 13.52}, "9": {"size": 24.0, "damax": 25.9, "damin": 24.0, "dw": 33.25, "m": 16.16}, "10": {"size": 30.0, "damax": 32.4, "damin": 30.0, "dw": 42.75, "m": 19.44}, "11": {"size": 36.0, "damax": 38.9, "damin": 36.0, "dw": 51.11, "m": 23.52}}, "1587": {"1": {"size": "M4", "damax": 4.6, "damin": 4.0, "dw": 5.9, "m": 2.9}, "2": {"size": "M5", "damax": 5.75, "damin": 5.0, "dw": 6.9, "m": 3.7}, "3": {"size": "M6", "damax": 6.75, "damin": 6.0, "dw": 8.9, "m": 4.7}, "4": {"size": "M8", "damax": 8.75, "damin": 8.0, "dw": 11.6, "m": 6.14}, "5": {"size": "M10", "damax": 10.8, "damin": 10.0, "dw": 14.6, "m": 7.64}, "6": {"size": "M12", "damax": 13.0, "damin": 12.0, "dw": 16.6, "m": 9.64}, "7": {"size": "M14", "damax": 15.1, "damin": 14.0, "dw": 19.6, "m": 10.3}, "8": {"size": "M16", "damax": 17.3, "damin": 16.0, "dw": 22.5, "m": 12.3}, "9": {"size": "M18", "damax": 19.5, "damin": 18.0, "dw": 24.9, "m": 14.3}, "10": {"size": "M20", "damax": 21.6, "damin": 20.0, "dw": 27.7, "m": 14.9}, "11": {"size": "M22", "damax": 23.7, "damin": 22.0, "dw": 31.4, "m": 16.9}, "12": {"size": "M24", "damax": 25.9, "damin": 24.0, "dw": 33.3, "m": 17.7}, "13": {"size": "M8x1", "damax": 8.75, "damin": 8.0, "dw": 11.6, "m": 6.14}, "14": {"size": "M10x1.25", "damax": 10.8, "damin": 10.0, "dw": 14.6, "m": 7.64}, "15": {"size": "M10x1.25", "damax": 10.8, "damin": 10.0, "dw": 14.6, "m": 7.64}, "16": {"size": "M12x1.5", "damax": 13.0, "damin": 12.0, "dw": 16.6, "m": 9.64}, "17": {"size": "M12x1.25", "damax": 13.0, "damin": 12.0, "dw": 16.6, "m": 9.64}, "18": {"size": "M14x1.5", "damax": 15.1, "damin": 14.0, "dw": 19.6, "m": 10.3}, "19": {"size": "M16x1.5", "damax": 17.3, "damin": 16.0, "dw": 22.5, "m": 12.3}, "20": {"size": "M18x2", "damax": 19.5, "damin": 18.0, "dw": 24.9, "m": 14.3}, "21": {"size": "M18x1.5", "damax": 19.5, "damin": 18.0, "dw": 24.9, "m": 14.3}, "22": {"size": "M20x2", "damax": 21.6, "damin": 20.0, "dw": 27.7, "m": 14.9}, "23": {"size": "M20x1.5", "damax": 21.6, "damin": 20.0, "dw": 27.7, "m": 14.9}, "24": {"size": "M22x2", "damax": 23.7, "damin": 22.0, "dw": 31.4, "m": 16.9}, "25": {"size": "M22x1.5", "damax": 23.7, "damin": 22.0, "dw": 31.4, "m": 16.9}, "26": {"size": "M24x2", "damax": 25.9, "damin": 24.0, "dw": 33.3, "m": 17.7}}, "": {}}